{"P1": {"labels": ["Article", "\u673a\u5668\u5b66\u4e60", "\u4eba\u5de5\u667a\u80fd"], "postTitle": "\u300aPython\u673a\u5668\u5b66\u4e60\u57fa\u7840\u6559\u7a0b\u300b\u81ea\u5b66\u7b14\u8bb0", "postUrl": "post/%E3%80%8APython-ji-qi-xue-xi-ji-chu-jiao-cheng-%E3%80%8B-zi-xue-bi-ji.html", "createdDate": "2025-04-05", "dateLabelColor": "#0969da"}, "labelColorDict": {"Article": "#e99695", "bug": "#d73a4a", "documentation": "#0075ca", "duplicate": "#cfd3d7", "enhancement": "#a2eeef", "good first issue": "#7057ff", "help wanted": "#008672", "invalid": "#e4e669", "question": "#d876e3", "wontfix": "#ffffff", "\u4eba\u5de5\u667a\u80fd": "#53A17E", "\u673a\u5668\u5b66\u4e60": "#605C04"}}